ma5_expert/__init__.py
ma5_expert/_version.py
ma5_expert/backend/__init__.py
ma5_expert/backend/ma5_backend.py
ma5_expert/cutflow/__init__.py
ma5_expert/cutflow/cut.py
ma5_expert/cutflow/objects.py
ma5_expert/cutflow/reader.py
ma5_expert/cutflow/table.py
ma5_expert/histogram/__init__.py
ma5_expert/histogram/bin.py
ma5_expert/histogram/histo.py
ma5_expert/histogram/reader.py
ma5_expert/pad/__init__.py
ma5_expert/pad/interface.py
ma5_expert/system/__init__.py
ma5_expert/system/exceptions.py
ma5_expert/system/logger.py
ma5_expert/tools/FoM.py
ma5_expert/tools/SafReader.py
ma5_expert/tools/__init__.py
ma5_expert-3.0.4.dist-info/LICENSE
ma5_expert-3.0.4.dist-info/METADATA
ma5_expert-3.0.4.dist-info/WHEEL
ma5_expert-3.0.4.dist-info/top_level.txt
ma5_expert-3.0.4.dist-info/RECORD
