Metadata-Version: 2.1
Name: ma5-expert
Version: 3.0.4
Summary: MadAnalysis 5 interpreter for Expert mode
Home-page: https://github.com/MadAnalysis/ma5_expert
Download-URL: https://github.com/MadAnalysis/ma5_expert/archive/refs/tags/v3.0.4.tar.gz
Author: Jack Y. Araz
Author-email: jack.araz@durham.ac.uk
License: MIT
Project-URL: Bug Tracker, https://github.com/MadAnalysis/ma5_expert/issues
Keywords: physics madanalysis5
Classifier: Intended Audience :: Science/Research
Classifier: License :: OSI Approved :: MIT License
Classifier: Operating System :: OS Independent
Classifier: Programming Language :: Python :: 3
Classifier: Topic :: Scientific/Engineering :: Physics
Requires-Python: >=3.8
License-File: LICENSE
Requires-Dist: numpy (>=1.21.6)
